README.md
setup.cfg
setup.py
shizen_gengo/__init__.py
shizen_gengo.egg-info/PKG-INFO
shizen_gengo.egg-info/SOURCES.txt
shizen_gengo.egg-info/dependency_links.txt
shizen_gengo.egg-info/requires.txt
shizen_gengo.egg-info/top_level.txt
shizen_gengo/explore/__init__.py
shizen_gengo/explore/explore_utils.py
shizen_gengo/preprocess_dataframe/__init__.py
shizen_gengo/preprocess_dataframe/dataframe_utils.py
shizen_gengo/preprocess_text/__init__.py
shizen_gengo/preprocess_text/nltkmodules.py
shizen_gengo/preprocess_text/text_utils.py