Metadata-Version: 2.1
Name: shizen-gengo
Version: 0.1.4
Summary: Python Library for common NLP Tasks
Home-page: https://github.com/raoulbia/shizen_gengo.git
Author: raoul biagioni
Author-email: raoulbia.research@gmail.com
License: 	gpl-3.0
Download-URL: https://github.com/raoulbia/shizen_gengo/archive/0.1.0.tar.gz
Project-URL: Documentation, https://shizen-gengo.readthedocs.io/en/latest/
Keywords: nlp,pandas,dataframe
Platform: UNKNOWN
Provides-Extra: docs
Provides-Extra: tests
